terraria_apis_objects/__init__.py
terraria_apis_objects/terraria_apis_objects.py
terraria_apis_objects-1.0.0.dist-info/LICENSE
terraria_apis_objects-1.0.0.dist-info/METADATA
terraria_apis_objects-1.0.0.dist-info/WHEEL
terraria_apis_objects-1.0.0.dist-info/top_level.txt
terraria_apis_objects-1.0.0.dist-info/RECORD
