Metadata-Version: 2.1
Name: terraria-apis-objects
Version: 1.0.0
Summary: Objects for terraria APIs
Home-page: https://gitlab.com/fkwilczek/terraria-apis-objects
Author: Filip K
Author-email: fkwilczek@gmail.com
License: GNU General Public License v3 (GPLv3)
Platform: UNKNOWN
Classifier: Programming Language :: Python :: 3
Classifier: Operating System :: OS Independent
Classifier: License :: OSI Approved :: GNU General Public License v3 (GPLv3)
License-File: LICENSE
